Lab7/Lab7.srcs/sources_1/new/RegisterFile.v
`timescale 1ns / 1ps
//////////////////////////////////////////////////////////////////////////////////
// Company: 
// Engineer: 
// 
// Create Date: 03/11/2026 02:50:15 PM
// Design Name: 
// Module Name: RegisterFile
// Project Name: 
// Target Devices: 
// Tool Versions: 
// Description: 
// 
// Dependencies: 
// 
// Revision:
// Revision 0.01 - File Created
// Additional Comments:
// 
//////////////////////////////////////////////////////////////////////////////////


module RegisterFile (
    input wire clk,
    input wire rst,
    input wire WriteEnable,
    input wire [4:0] rs1,
    input wire [4:0] rs2,
    input wire [4:0] rd,
    input wire [31:0] WriteData,
    output wire [31:0] ReadData1,
    output wire [31:0] readData2
);

    reg [31:0] regs [31:0];
    
    integer i;

    assign ReadData1 = (rs1 == 5'd0) ? 32'b0 : regs[rs1];
    assign readData2 = (rs2 == 5'd0) ? 32'b0 : regs[rs2];

    always @(posedge clk) begin
        if (rst) begin
            for (i = 0; i < 32; i = i + 1) begin
                regs[i] <= 32'b0;
            end
        end 
        else if (WriteEnable && (rd != 5'd0)) begin
            regs[rd] <= WriteData;
        end
    end

endmodule

Lab7/Lab7.srcs/sim_1/new/RegisterFile_tb.v
`timescale 1ns / 1ps
//////////////////////////////////////////////////////////////////////////////////
// Company: 
// Engineer: 
// 
// Create Date: 03/12/2026 09:36:19 AM
// Design Name: 
// Module Name: RegisterFile_tb
// Project Name: 
// Target Devices: 
// Tool Versions: 
// Description: 
// 
// Dependencies: 
// 
// Revision:
// Revision 0.01 - File Created
// Additional Comments:
// 
//////////////////////////////////////////////////////////////////////////////////


`timescale 1ns / 1ps

module RegisterFile_tb;

    reg clk;
    reg rst;
    reg WriteEnable;
    reg [4:0] rs1;
    reg [4:0] rs2;
    reg [4:0] rd;
    reg [31:0] WriteData;

    wire [31:0] ReadData1;
    wire [31:0] readData2;

    RegisterFile uut (
        .clk(clk),
        .rst(rst),
        .WriteEnable(WriteEnable),
        .rs1(rs1),
        .rs2(rs2),
        .rd(rd),
        .WriteData(WriteData),
        .ReadData1(ReadData1),
        .readData2(readData2)
    );

    always #5 clk = ~clk;

    initial begin

        clk = 0;
        rst = 0;
        WriteEnable = 0;
        rs1 = 0;
        rs2 = 0;
        rd = 0;
        WriteData = 0;

        rst = 1;
        #10;
        rst = 0;
        
        rd = 5'd5;
        WriteData = 32'hDEADBEEF;
        WriteEnable = 1;
        #10;
        WriteEnable = 0;
        
        rs1 = 5'd5;
        #5;

        rd = 5'd0;
        WriteData = 32'hBADCAFE0;
        WriteEnable = 1;
        #10;
        WriteEnable = 0;

        rs2 = 5'd0;
        #5;

        rd = 5'd10;
        WriteData = 32'h12345678;
        WriteEnable = 1;
        #10;
        WriteEnable = 0;

        rs1 = 5'd5;
        rs2 = 5'd10;
        #5;

        rd = 5'd5;
        WriteData = 32'h0000BEEF;
        WriteEnable = 1;
        #10;
        WriteEnable = 0;

        rs1 = 5'd5;
        #5;

        rst = 1;
        #10;
        rst = 0;
        
        rs1 = 5'd5;
        rs2 = 5'd10;
        #5;
        $finish;
    end

endmodule

Lab7/Lab7.sim/sim_1/behav/xsim/register_file.vcd
$date
   Thu Mar 12 09:39:54 2026
$end
$version
  2020.1
$end
$timescale
  1ps
$end
$scope module RegisterFile_tb $end
$var reg 1 ! clk $end
$var reg 1 " rst $end
$var reg 1 # WriteEnable $end
$var reg 5 $ rs1 [4:0] $end
$var reg 5 % rs2 [4:0] $end
$var reg 5 & rd [4:0] $end
$var reg 32 ' WriteData [31:0] $end
$var wire 32 ( ReadData1 [31:0] $end
$var wire 32 ) readData2 [31:0] $end
$scope module uut $end
$var wire 1 * clk $end
$var wire 1 + rst $end
$var wire 1 , WriteEnable $end
$var wire 5 - rs1 [4:0] $end
$var wire 5 . rs2 [4:0] $end
$var wire 5 / rd [4:0] $end
$var wire 32 0 WriteData [31:0] $end
$var wire 32 ( ReadData1 [31:0] $end
$var wire 32 ) readData2 [31:0] $end
$var integer 32 1 i $end
$upscope $end
$upscope $end
$enddefinitions $end
#0
$dumpvars
0!
1"
0#
b0 $
b0 %
b0 &
b0 '
b0 (
b0 )
0*
1+
0,
b0 -
b0 .
b0 /
b0 0
bx 1
$end
#5000
1!
1*
#10000
0!
0"
1#
b101 &
b11011110101011011011111011101111 '
0*
0+
1,
b101 /
b11011110101011011011111011101111 0
#15000
1!
1*
#20000
0!
0#
b101 $
b11011110101011011011111011101111 (
0*
0,
b101 -
#25000
1!
1#
b0 &
b10111010110111001010111111100000 '
1*
1,
b0 /
b10111010110111001010111111100000 0
#30000
0!
0*
#35000
1!
0#
b0 %
1*
0,
#40000
0!
1#
b1010 &
b10010001101000101011001111000 '
0*
1,
b1010 /
b10010001101000101011001111000 0
#45000
1!
1*
#50000
0!
0#
b101 $
b1010 %
b10010001101000101011001111000 )
0*
0,
b1010 .
#55000
1!
1#
b101 &
b1011111011101111 '
b1011111011101111 (
1*
1,
b101 /
b1011111011101111 0
#60000
0!
0*
#65000
1!
0#
b101 $
1*
0,
#70000
0!
1"
0*
1+
#75000
1!
b0 (
b0 )
1*
#80000
0!
0"
b101 $
b1010 %
0*
0+
